[{"name":"freakpants' list of disaster","id":"0","description":"A list of music enjoyed by the creator of MusicGuess.","amount_of_tracks":637,"album_art":["http:\/\/cdn-images.deezer.com\/images\/cover\/05a186e0a859a36f9cd51cdae2158fe1\/1000x1000-000000-80-0-0.jpg","https:\/\/cdns-images.dzcdn.net\/images\/cover\/5f3fc65fa26962b1c2e97519a953d621\/1000x1000-000000-80-0-0.jpg","http:\/\/e-cdn-images.deezer.com\/images\/cover\/2abcc790ccb86e8f8615b3f7ea305ee5\/1000x1000-000000-80-0-0.jpg","http:\/\/cdn-images.deezer.com\/images\/cover\/e550f19538f883c6663e1f1da24b7359\/1000x1000-000000-80-0-0.jpg"]},{"name":"Popular Stuff","id":"1","description":"Music that a lot of people like","amount_of_tracks":416,"album_art":["http:\/\/cdn-images.deezer.com\/images\/cover\/c8d985893532eb4b79cab4a5ec7b241a\/1000x1000-000000-80-0-0.jpg","https:\/\/e-cdns-images.dzcdn.net\/images\/cover\/51a266eaeac1c5062720057cbb68bbec\/1000x1000-000000-80-0-0.jpg","http:\/\/cdn-images.deezer.com\/images\/cover\/dfdd0fa891bd126497b48c27ed15bf88\/1000x1000-000000-80-0-0.jpg","http:\/\/cdn-images.deezer.com\/images\/cover\/570ffa9c0f7cdce0fb9b00408273769e\/1000x1000-000000-80-0-0.jpg"]},{"name":"90's","id":"2","description":"Only kids will get this","amount_of_tracks":126,"album_art":["https:\/\/e-cdns-images.dzcdn.net\/images\/cover\/dddb04bdce11a28c0538c44fc950caab\/1000x1000-000000-80-0-0.jpg","https:\/\/cdns-images.dzcdn.net\/images\/cover\/4645b72275fc902d8f2ee5d298bcfac0\/1000x1000-000000-80-0-0.jpg","http:\/\/cdn-images.deezer.com\/images\/cover\/8edea087f65bafb27873bc3b0eae37ec\/1000x1000-000000-80-0-0.jpg","https:\/\/cdns-images.dzcdn.net\/images\/cover\/08a906bd35e5707ef08ceed3e36db1c7\/1000x1000-000000-80-0-0.jpg"]},{"name":"Dance Music","id":"3","description":"Electronic Dance Music, mostly Trance.","amount_of_tracks":161,"album_art":["http:\/\/cdn-images.deezer.com\/images\/cover\/6aef295de6f9af017647b3bda97a60f2\/1000x1000-000000-80-0-0.jpg","https:\/\/e-cdns-images.dzcdn.net\/images\/cover\/f9e1d685d56b54dbb91e956215fb4880\/1000x1000-000000-80-0-0.jpg","http:\/\/i.imgur.com\/4Z6Zxsy.jpg","http:\/\/cdn-images.deezer.com\/images\/cover\/589d31e2600952e5ad7428fa24728b8b\/1000x1000-000000-80-0-0.jpg"]},{"name":"Trance","id":"4","description":"Beats & Vocals","amount_of_tracks":100,"album_art":["https:\/\/e-cdns-images.dzcdn.net\/images\/cover\/c63908ce8419db65395e1a58cc52a9d7\/1000x1000-000000-80-0-0.jpg","https:\/\/e-cdns-images.dzcdn.net\/images\/cover\/29f566cab6714b57b4056d69233b3b84\/1000x1000-000000-80-0-0.jpg","http:\/\/i.imgur.com\/aAAqSM9g.jpg","https:\/\/i.imgur.com\/TD4RTgq.jpg"]},{"name":"Rock & Metal","id":"5","description":"Mostly of the softer persuasion though","amount_of_tracks":88,"album_art":["http:\/\/e-cdn-images.deezer.com\/images\/cover\/6c742cc292a8a4cd9f0585273e9dc92b\/1000x1000-000000-80-0-0.jpg","http:\/\/e-cdn-images.deezer.com\/images\/cover\/92c04572b566d90a7e24f76a63566ae3\/1000x1000-000000-80-0-0.jpg","http:\/\/i.imgur.com\/Cerplvjg.jpg","http:\/\/i.imgur.com\/Cerplvjg.jpg"]},{"name":"Deutsch","id":"7","description":"German Songs","amount_of_tracks":121,"album_art":["https:\/\/e-cdns-images.dzcdn.net\/images\/cover\/ec18f4c556cee51305ec3f2d4b988c7a\/1000x1000-000000-80-0-0.jpg","http:\/\/cdn-images.deezer.com\/images\/cover\/36cb1ff6d13d1ad02ca3e8d127d64511\/1000x1000-000000-80-0-0.jpg","https:\/\/e-cdns-images.dzcdn.net\/images\/cover\/03a0a617e48f4d5bd5322e610fb50870\/1000x1000-000000-80-0-0.jpg","https:\/\/cdns-images.dzcdn.net\/images\/cover\/c5296cf92e6bf7a228d24b2e311fba5a\/1000x1000-000000-80-0-0.jpg"]},{"name":"70's","id":"9","description":"Rock'n Roll & Funk is born","amount_of_tracks":101,"album_art":["http:\/\/i.imgur.com\/wAJjvZh.jpg","https:\/\/e-cdns-images.dzcdn.net\/images\/cover\/da60ddc1b07e8b9ec42641de5c602b57\/1000x1000-000000-80-0-0.jpg","https:\/\/e-cdns-images.dzcdn.net\/images\/cover\/e6f5bc9660b61f7e99c8eb3a108a74f8\/1000x1000-000000-80-0-0.jpg","https:\/\/e-cdns-images.dzcdn.net\/images\/cover\/1c8adc5ca978db9e7a07e61de2becd3f\/1000x1000-000000-80-0-0.jpg"]},{"name":"80's","id":"10","description":"The age of MTV","amount_of_tracks":102,"album_art":["http:\/\/i.imgur.com\/SQBfnK3.jpg","https:\/\/cdns-images.dzcdn.net\/images\/cover\/34a285a96fbb84bf85030f25e5dff69b\/1000x1000-000000-80-0-0.jpg","http:\/\/i.imgur.com\/ITVZnSa.jpg","https:\/\/cdns-images.dzcdn.net\/images\/cover\/1d88b7de206eab4781f878d320ecf8a8\/1000x1000-000000-80-0-0.jpg"]},{"name":"2000's","id":"11","description":"The best and the worst decade.","amount_of_tracks":104,"album_art":["http:\/\/cdn-images.deezer.com\/images\/cover\/d468c03b8c03bf5edb8c310a7dd56b8c\/1000x1000-000000-80-0-0.jpg","http:\/\/cdn-images.deezer.com\/images\/cover\/dc7637895e982429854e76d654fbf0fc\/1000x1000-000000-80-0-0.jpg","https:\/\/e-cdns-images.dzcdn.net\/images\/cover\/cc24d60a998e1a296f0c22efa8ddffd2\/1000x1000-000000-80-0-0.jpg","https:\/\/cdns-images.dzcdn.net\/images\/cover\/71698262cce4bb1c0e3d25e0707ed092\/1000x1000-000000-80-0-0.jpg"]},{"name":"Swiss","id":"12","description":"Songs from Switzerland. mostly in Swiss German","amount_of_tracks":103,"album_art":["http:\/\/i.imgur.com\/cKIVyq2.jpg","https:\/\/e-cdns-images.dzcdn.net\/images\/cover\/7da75988fda0b119d4af49a02b58fc87\/1000x1000-000000-80-0-0.jpg","http:\/\/i.imgur.com\/ECrKs4rg.jpg","https:\/\/e-cdns-images.dzcdn.net\/images\/cover\/8386223ff60e5b4f304f162e399558df\/1000x1000-000000-80-0-0.jpg"]}]