[{"artist":"\u00d6 la Pal\u00f6ma Boys","title":"\u00d6 la Pal\u00f6ma (Radio Edit)","preview_url":"http:\/\/a1910.phobos.apple.com\/us\/r1000\/049\/Music4\/v4\/bd\/bf\/8d\/bdbf8de8-ae14-59b6-e22d-41e7e81494f4\/mzaf_1126034317141828792.plus.aac.p.m4a","album":"\u00d6 la Pal\u00f6ma","album_art":"http:\/\/is2.mzstatic.com\/image\/thumb\/Music\/v4\/03\/01\/22\/030122d1-bd16-ebc2-614c-8cc95bffb130\/source\/100x100bb.jpg","buy_link":"https:\/\/itunes.apple.com\/us\/album\/%C3%B6-la-pal%C3%B6ma-radio-edit\/id74378493?i=74378431&uo=4"},{"artist":"Die \u00c4rzte","title":"M\u00e4nner sind Schweine","preview_url":"http:\/\/a836.phobos.apple.com\/us\/r30\/Music\/8d\/b4\/67\/mzm.dvpawrje.aac.p.m4a","album":"13","album_art":"http:\/\/is2.mzstatic.com\/image\/thumb\/Music\/v4\/f5\/50\/34\/f5503469-f818-cec5-eee1-bdd6e7a8cb58\/source\/100x100bb.jpg","buy_link":"https:\/\/itunes.apple.com\/us\/album\/m%C3%A4nner-sind-schweine\/id295345571?i=295345669&uo=4"},{"artist":"Baha Men","title":"Who Let the Dog's Out?","preview_url":"http:\/\/a208.phobos.apple.com\/us\/r30\/Music\/7b\/37\/2d\/mzm.jndhklxb.aac.p.m4a","album":"Who Let the Dog's Out? - Single","album_art":"http:\/\/is4.mzstatic.com\/image\/thumb\/Music\/v4\/53\/df\/e3\/53dfe3a6-37a4-fa80-28a1-e8d7c0b7385a\/source\/100x100bb.jpg","buy_link":"https:\/\/itunes.apple.com\/us\/album\/who-let-the-dogs-out\/id365346229?i=365346245&uo=4"},{"artist":"Buddy","title":"Ab in den S\u00fcden","preview_url":"http:\/\/a1077.phobos.apple.com\/us\/r30\/Music\/v4\/2a\/43\/4e\/2a434ea7-d18d-41c8-835a-2aa75f514663\/mzaf_172248439866118834.plus.aac.p.m4a","album":"Ab in den S\u00fcden - Single","album_art":"http:\/\/is1.mzstatic.com\/image\/thumb\/Music4\/v4\/37\/1f\/58\/371f5868-906e-eed7-42f1-21684a8aee5f\/source\/100x100bb.jpg","buy_link":"https:\/\/itunes.apple.com\/us\/album\/ab-in-den-s%C3%BCden\/id869345470?i=869345495&uo=4"},{"artist":"Chumbawamba","title":"Tubthumping","preview_url":"http:\/\/a920.phobos.apple.com\/us\/r30\/Music\/62\/bc\/85\/mzm.accyntlx.aac.p.m4a","album":"Tubthumper","album_art":"http:\/\/is5.mzstatic.com\/image\/thumb\/Music\/v4\/20\/81\/d3\/2081d3fb-2652-3477-0f10-64e8f541b470\/source\/100x100bb.jpg","buy_link":"https:\/\/itunes.apple.com\/us\/album\/tubthumping\/id99935?i=99908&uo=4"},{"artist":"Lordi","title":"Hard Rock Hallelujah","preview_url":"http:\/\/a1668.phobos.apple.com\/us\/r30\/Music\/f5\/2d\/90\/mzm.wwqgistv.aac.p.m4a","album":"The Hills Have Eyes 2 - The Album","album_art":"http:\/\/is5.mzstatic.com\/image\/thumb\/Music\/v4\/46\/bd\/fa\/46bdfa8c-f166-678e-ec0d-4e2726d565d3\/source\/100x100bb.jpg","buy_link":"https:\/\/itunes.apple.com\/us\/album\/hard-rock-hallelujah\/id389516373?i=389516413&uo=4"},{"artist":"Massive T\u00f6ne","title":"Cruisen","preview_url":"http:\/\/a88.phobos.apple.com\/us\/r30\/Music\/v4\/43\/cc\/ab\/43ccabe2-a0d1-6888-3915-bda0a0af2df9\/mzaf_384856560541657544.plus.aac.p.m4a","album":"Mt3","album_art":"http:\/\/is4.mzstatic.com\/image\/thumb\/Music\/v4\/d1\/26\/d2\/d126d253-5b65-b33b-e7d4-3b7acf1cdbb9\/source\/100x100bb.jpg","buy_link":"https:\/\/itunes.apple.com\/us\/album\/cruisen\/id160606017?i=160606019&uo=4"},{"artist":"Mittermeier vs. Guano Babes","title":"Kumba Yo!","preview_url":"http:\/\/a1053.phobos.apple.com\/us\/r30\/Music\/f9\/84\/db\/mzm.anoxticd.aac.p.m4a","album":"Planet of the Apes - Best of Guano Apes","album_art":"http:\/\/is1.mzstatic.com\/image\/thumb\/Music\/v4\/88\/c8\/c0\/88c8c001-7bfe-f97e-1fcf-d5222d69ce40\/source\/100x100bb.jpg","buy_link":"https:\/\/itunes.apple.com\/us\/album\/kumba-yo\/id281689230?i=281689258&uo=4"},{"artist":"Panjabi MC","title":"Beware of the Boys (Mundian to Bach Ke)","preview_url":"http:\/\/a1466.phobos.apple.com\/us\/r30\/Music\/v4\/2a\/95\/02\/2a950218-4fe6-efad-b175-9ed7337274ea\/mzaf_8383309657718307454.aac.m4a","album":"Beware","album_art":"http:\/\/is5.mzstatic.com\/image\/thumb\/Music\/v4\/04\/35\/14\/0435140b-15aa-771a-edf7-2b4dea1b6f96\/source\/100x100bb.jpg","buy_link":"https:\/\/itunes.apple.com\/us\/album\/beware-of-the-boys-mundian-to-bach-ke\/id310343784?i=310343997&uo=4"},{"artist":"Stefan Raab","title":"Wadde hadde dudde da?","preview_url":"http:\/\/a1900.phobos.apple.com\/us\/r1000\/097\/Music2\/v4\/0d\/88\/5a\/0d885aa9-deec-fca2-f0dd-4203853a2f89\/mzaf_8626905648267873698.aac.m4a","album":"TV Total - Das Album","album_art":"http:\/\/is2.mzstatic.com\/image\/thumb\/Music\/v4\/80\/4d\/d8\/804dd815-0eb3-a75b-06c6-428bd42aa9c3\/source\/100x100bb.jpg","buy_link":"https:\/\/itunes.apple.com\/us\/album\/wadde-hadde-dudde-da\/id74379397?i=74378728&uo=4"}]