[{"name":"freakpants' list of disaster","id":"0","description":"A list of music enjoyed by the creator of MusicGuess.","amount_of_tracks":637,"album_art":["https:\/\/e-cdns-images.dzcdn.net\/images\/cover\/be7a8eaf564cca20a4e76a72cb39aa74\/1000x1000-000000-80-0-0.jpg","http:\/\/e-cdn-images.deezer.com\/images\/cover\/88a2e65c4b10967a465c49f0d4d91da1\/1000x1000-000000-80-0-0.jpg","http:\/\/cdn-images.deezer.com\/images\/cover\/9c84a41add99eea52c0db2c4fa49156d\/1000x1000-000000-80-0-0.jpg","http:\/\/cdn-images.deezer.com\/images\/cover\/887f83f9ed9c9c988d62f5c7fc0a4dfa\/1000x1000-000000-80-0-0.jpg"]},{"name":"Popular Stuff","id":"1","description":"Music that a lot of people like","amount_of_tracks":416,"album_art":["https:\/\/e-cdns-images.dzcdn.net\/images\/cover\/6270191b9efc08ae3f6a1418a1edd5ee\/1000x1000-000000-80-0-0.jpg","http:\/\/cdn-images.deezer.com\/images\/cover\/cba9e9707a6d0652c641b3c40a6e419e\/1000x1000-000000-80-0-0.jpg","http:\/\/e-cdn-images.deezer.com\/images\/cover\/3b707034b3a1cd1bb8323d051b2afe86\/1000x1000-000000-80-0-0.jpg","http:\/\/cdn-images.deezer.com\/images\/cover\/19b318cd87d55fbe2c97113b919b1758\/1000x1000-000000-80-0-0.jpg"]},{"name":"90's","id":"2","description":"Only kids will get this","amount_of_tracks":126,"album_art":["https:\/\/cdns-images.dzcdn.net\/images\/cover\/4645b72275fc902d8f2ee5d298bcfac0\/1000x1000-000000-80-0-0.jpg","http:\/\/i.imgur.com\/egLsZj7.jpg","http:\/\/i.imgur.com\/z82PEus.jpg","http:\/\/cdn-images.deezer.com\/images\/cover\/536b9d6d733e60874306ad63d6c47c52\/1000x1000-000000-80-0-0.jpg"]},{"name":"Dance Music","id":"3","description":"Electronic Dance Music, mostly Trance.","amount_of_tracks":161,"album_art":["http:\/\/cdn-images.deezer.com\/images\/cover\/7d4a24e294bb3c228ad96dd75512e2f0\/1000x1000-000000-80-0-0.jpg","http:\/\/cdn-images.deezer.com\/images\/cover\/b600a368afe9c8d36d4f10c0ca5b7b83\/1000x1000-000000-80-0-0.jpg","https:\/\/e-cdns-images.dzcdn.net\/images\/cover\/1d9f1b70e8c459705f9fbb6fae2fc475\/1000x1000-000000-80-0-0.jpg","http:\/\/i.imgur.com\/4Z6Zxsy.jpg"]},{"name":"Trance","id":"4","description":"Beats & Vocals","amount_of_tracks":100,"album_art":["https:\/\/e-cdns-images.dzcdn.net\/images\/cover\/443f534139ad61f70a94bae702bb072c\/1000x1000-000000-80-0-0.jpg","http:\/\/i.imgur.com\/aAAqSM9g.jpg","https:\/\/e-cdns-images.dzcdn.net\/images\/cover\/a6baa50a70fae62f8d217a6690babd46\/1000x1000-000000-80-0-0.jpg","https:\/\/cdns-images.dzcdn.net\/images\/cover\/9787da9a6a9595510967858dd8efd6ee\/1000x1000-000000-80-0-0.jpg"]},{"name":"Rock & Metal","id":"5","description":"Mostly of the softer persuasion though","amount_of_tracks":101,"album_art":["http:\/\/cdn-images.deezer.com\/images\/cover\/a60a9399980ad3ec3151a2b672e93fcf\/1000x1000-000000-80-0-0.jpg","https:\/\/e-cdns-images.dzcdn.net\/images\/cover\/751c93f7134fcd00dd6d879f01ff2fde\/1000x1000-000000-80-0-0.jpg","https:\/\/cdns-images.dzcdn.net\/images\/cover\/bb1cf562bb346d5ab77fec9d7ff08a1a\/1000x1000-000000-80-0-0.jpg","http:\/\/cdn-images.deezer.com\/images\/cover\/96d3d59b5a673df7ee379b61ac35e74c\/1000x1000-000000-80-0-0.jpg"]},{"name":"Deutsch","id":"7","description":"German Songs","amount_of_tracks":121,"album_art":["https:\/\/e-cdns-images.dzcdn.net\/images\/cover\/398b2ce51c10473786c1582f7aeb2fb2\/1000x1000-000000-80-0-0.jpg","https:\/\/e-cdns-images.dzcdn.net\/images\/cover\/8ae19d0a59b5c05fcd0f7e052eec9fc1\/1000x1000-000000-80-0-0.jpg","http:\/\/i.imgur.com\/WVxcqq1.jpg","http:\/\/cdn-images.deezer.com\/images\/cover\/71900e6e2ced543bc0b588feabf2c61c\/1000x1000-000000-80-0-0.jpg"]},{"name":"70's","id":"9","description":"Rock'n Roll & Funk is born","amount_of_tracks":101,"album_art":["https:\/\/e-cdns-images.dzcdn.net\/images\/cover\/14c4093d20e4147cb1b07d001239eba5\/1000x1000-000000-80-0-0.jpg","http:\/\/i.imgur.com\/YwldHCa.jpg","https:\/\/e-cdns-images.dzcdn.net\/images\/cover\/2b706158a66dee36b7eb874eb013dc48\/1000x1000-000000-80-0-0.jpg","https:\/\/e-cdns-images.dzcdn.net\/images\/cover\/6cefdc795fa3f38078900eabc5db956c\/1000x1000-000000-80-0-0.jpg"]},{"name":"80's","id":"10","description":"The age of MTV","amount_of_tracks":103,"album_art":["https:\/\/e-cdns-images.dzcdn.net\/images\/cover\/6ce6234006881b6607dcdbdbca92af02\/1000x1000-000000-80-0-0.jpg","http:\/\/i.imgur.com\/ITVZnSa.jpg","https:\/\/cdns-images.dzcdn.net\/images\/cover\/79238f7c460428199eb204587f6759a2\/1000x1000-000000-80-0-0.jpg","https:\/\/e-cdns-images.dzcdn.net\/images\/cover\/25b602a6bea831c7fe8129b6697e413f\/1000x1000-000000-80-0-0.jpg"]},{"name":"2000's","id":"11","description":"The best and the worst decade.","amount_of_tracks":104,"album_art":["http:\/\/cdn-images.deezer.com\/images\/cover\/2d38e9d1e1a07e69e0bad3302eeb8722\/1000x1000-000000-80-0-0.jpg","https:\/\/e-cdns-images.dzcdn.net\/images\/cover\/02d0ed56b2485b5f58fa63e6a3bbb73c\/1000x1000-000000-80-0-0.jpg","http:\/\/i.imgur.com\/1cSRLCd.jpg","https:\/\/cdns-images.dzcdn.net\/images\/cover\/8a337961f767eaaa08c44143c342ac2f\/1000x1000-000000-80-0-0.jpg"]},{"name":"Swiss","id":"12","description":"Songs from Switzerland. mostly in Swiss German","amount_of_tracks":103,"album_art":["http:\/\/e-cdn-images.deezer.com\/images\/cover\/d84b66cf6026142ec63e458518cc06d3\/1000x1000-000000-80-0-0.jpg","https:\/\/e-cdns-images.dzcdn.net\/images\/cover\/dcd0c53ada69b77781603fa58e396c19\/1000x1000-000000-80-0-0.jpg","https:\/\/e-cdns-images.dzcdn.net\/images\/cover\/08a0a3532b40ddbe82104c80133910b2\/1000x1000-000000-80-0-0.jpg","https:\/\/e-cdns-images.dzcdn.net\/images\/cover\/5e0c4f49923d4db7d3cdf7ccd5c46794\/1000x1000-000000-80-0-0.jpg"]}]